<?xml version="1.0" encoding="UTF-8"?>

<!-- generated on Tue Mar  5 11:57:36 2019 by Eclipse SUMO GUI Version 1.0.1
<configuration xmlns:xsi="http://www.w3.org/2001/XMLSchema-instance" xsi:noNamespaceSchemaLocation="http://sumo.dlr.de/xsd/sumoConfiguration.xsd">

    <input>
        <net-file value="../Resources/FiveLanes/fivelanes.net.xml"/>
        <route-files value="../Resources/FiveLanes/100v-trips.trips.xml"/>
    </input>

    <output>
        <output-prefix value="0"/>
        <tripinfo-output value="../Resources/FiveLanes/tripinfos.xml"/>
        <lanechange-output value="lanechange.xml"/>
    </output>

    <processing>
        <ignore-route-errors value="true"/>
    </processing>

    <report>
        <verbose value="true"/>
        <duration-log.statistics value="true"/>
        <no-step-log value="true"/>
    </report>

    <traci_server>
        <remote-port value="53777"/>
    </traci_server>

    <random_number>
        <seed value="275"/>
    </random_number>

    <gui_only>
        <quit-on-end value="true"/>
    </gui_only>

</configuration>
-->

<lanechanges>
    <change id="0" type="DEFAULT_VEHTYPE" time="6.00" from="gneE0_2" to="gneE0_1" dir="-1" speed="11.28" pos="43.70" reason="keepRight" leaderGap="None" leaderSecureGap="None" followerGap="12.46" followerSecureGap="1.69" origLeaderGap="None" origLeaderSecureGap="None"/>
    <change id="1" type="DEFAULT_VEHTYPE" time="7.00" from="gneE0_1" to="gneE0_0" dir="-1" speed="9.75" pos="35.99" reason="keepRight" leaderGap="None" leaderSecureGap="None" followerGap="None" followerSecureGap="None" origLeaderGap="16.01" origLeaderSecureGap="2.64"/>
    <change id="1" type="DEFAULT_VEHTYPE" time="11.00" from="gneE0_0" to="gneE0_1" dir="1" speed="18.05" pos="94.86" reason="speedGain" leaderGap="27.74" leaderSecureGap="15.74" followerGap="56.41" followerSecureGap="0.00" origLeaderGap="None" origLeaderSecureGap="None"/>
    <change id="0" type="DEFAULT_VEHTYPE" time="12.00" from="gneE0_1" to="gneE0_0" dir="-1" speed="18.84" pos="146.44" reason="keepRight" leaderGap="None" leaderSecureGap="None" followerGap="105.19" followerSecureGap="0.00" origLeaderGap="None" origLeaderSecureGap="None"/>
    <change id="13" type="DEFAULT_VEHTYPE" time="32.00" from="gneE0_3" to="gneE0_2" dir="-1" speed="24.96" pos="290.57" reason="traci|urgent" leaderGap="104.86" leaderSecureGap="20.34" followerGap="26.04" followerSecureGap="20.79" origLeaderGap="211.07" origLeaderSecureGap="30.89"/>
</lanechanges>
